minimalmodbus.py
minimalmodbus-2.1.0.dist-info/LICENSE
minimalmodbus-2.1.0.dist-info/WHEEL
minimalmodbus-2.1.0.dist-info/METADATA
minimalmodbus-2.1.0.dist-info/RECORD
