Metadata-Version: 2.1
Name: minimalmodbus
Version: 2.1.0
Summary: Easy-to-use Modbus RTU and Modbus ASCII implementation for Python
Keywords: minimalmodbus,modbus,modbus-serial,modbus-RTU,modbus-ASCII
Author: Jonas Berg
Requires-Python: >=3.8
Classifier: Development Status :: 5 - Production/Stable
Classifier: Intended Audience :: Developers
Classifier: Intended Audience :: Information Technology
Classifier: Intended Audience :: Science/Research
Classifier: Intended Audience :: Manufacturing
Classifier: License :: OSI Approved :: Apache Software License
Classifier: Natural Language :: English
Classifier: Operating System :: OS Independent
Classifier: Operating System :: POSIX
Classifier: Operating System :: Microsoft :: Windows
Classifier: Operating System :: MacOS :: MacOS X
Classifier: Programming Language :: Python
Classifier: Programming Language :: Python :: 3
Classifier: Programming Language :: Python :: 3.8
Classifier: Programming Language :: Python :: 3.9
Classifier: Programming Language :: Python :: 3.10
Classifier: Programming Language :: Python :: 3.11
Classifier: Programming Language :: Python :: 3.12
Classifier: Topic :: Communications
Classifier: Topic :: Home Automation
Classifier: Topic :: Scientific/Engineering
Classifier: Topic :: Software Development :: Libraries
Classifier: Topic :: Software Development :: Libraries :: Python Modules
Classifier: Topic :: System :: Hardware :: Hardware Drivers
Classifier: Topic :: Terminals :: Serial
Requires-Dist: pyserial>=3.0
Project-URL: Changelog, https://github.com/pyhys/minimalmodbus/blob/master/HISTORY.rst
Project-URL: Documentation, https://minimalmodbus.readthedocs.io
Project-URL: Homepage, https://github.com/pyhys/minimalmodbus
